midnight_framework/__init__.py
midnight_framework/cli.py
midnight_framework/generator.py
midnight_framework/templates/main.py
midnight_framework/templates/Buttons/AboutButtons.py
midnight_framework/templates/cogs/about.py
midnight_framework/templates/core/enums.py
midnight_framework-0.1.1.dist-info/METADATA
midnight_framework-0.1.1.dist-info/WHEEL
midnight_framework-0.1.1.dist-info/entry_points.txt
midnight_framework-0.1.1.dist-info/top_level.txt
midnight_framework-0.1.1.dist-info/RECORD
