Metadata-Version: 2.4
Name: midnight-framework
Version: 0.1.1
Summary: Framework for quickly creating Discord bots with Disnake
Home-page: https://github.com/z0nyx/midnight-framework
Author: z0nyx
Author-email: midnight.framework@gmail.com
Keywords: discord bot framework disnake
Classifier: Development Status :: 3 - Alpha
Classifier: Intended Audience :: Developers
Classifier: License :: OSI Approved :: MIT License
Classifier: Programming Language :: Python :: 3.8
Classifier: Programming Language :: Python :: 3.9
Classifier: Programming Language :: Python :: 3.10
Classifier: Operating System :: OS Independent
Requires-Python: >=3.8
Requires-Dist: disnake>=2.8.0
Requires-Dist: python-dotenv>=0.19.0
Requires-Dist: colorama>=0.4.4
Dynamic: author
Dynamic: author-email
Dynamic: classifier
Dynamic: description
Dynamic: description-content-type
Dynamic: home-page
Dynamic: keywords
Dynamic: requires-dist
Dynamic: requires-python
Dynamic: summary
